simplesmtp/__init__.py
simplesmtp/core.py
simplesmtp/util.py
simplesmtp-0.0.3.dist-info/LICENSE
simplesmtp-0.0.3.dist-info/METADATA
simplesmtp-0.0.3.dist-info/WHEEL
simplesmtp-0.0.3.dist-info/top_level.txt
simplesmtp-0.0.3.dist-info/RECORD
