Metadata-Version: 2.1
Name: simplesmtp
Version: 0.0.3
Summary: A very simple class to send e-mails using the SMTP Python Lib
Home-page: https://github.com/andidevel/simplesmtp
Author: Anderson R. Livramento
Author-email: andi.devel@gmail.com
License: Apache 2.0
Platform: UNKNOWN
Classifier: Development Status :: 3 - Alpha
Classifier: Intended Audience :: Developers
Classifier: License :: OSI Approved :: Apache Software License
Classifier: Programming Language :: Python :: 2.7
Classifier: Programming Language :: Python :: 3
Classifier: Programming Language :: Python :: 3.4
Classifier: Programming Language :: Python :: 3.5
Classifier: Programming Language :: Python :: 3.6
Provides-Extra: testing
